django_l10n-0.0.7.dist-info/METADATA
django_l10n-0.0.7.dist-info/RECORD
django_l10n-0.0.7.dist-info/WHEEL
django_l10n-0.0.7.dist-info/top_level.txt
djl10n/__init__.py
djl10n/helpers.py
djl10n/utils.py
djl10n/views.py
djl10n/management/__init__.py
djl10n/management/commands/__init__.py
djl10n/management/commands/migratelocalize.py
djl10n/templatetags/__init__.py
djl10n/templatetags/localize.py
