Metadata-Version: 2.1
Name: django-l10n
Version: 0.0.7
Summary: A different approach to Django localization
Home-page: https://github.com/ralkan/django-l10n
Author: Resul Alkan
Author-email: me@resulalkan.com
License: MIT
Download-URL: https://github.com/ralkan/django-l10n/tarball/0.0.7
Keywords: django,l10n,i18n,django language,django localization
Platform: UNKNOWN
Requires-Dist: Django (==1.7.10)
Requires-Dist: toml (==0.9.4)
